<!DOCTYPE BirthData>
<BirthData>
 <BirthInfo><FirstName>Earl</FirstName>
  <LastName>Anthony</LastName>
  <Anka>1</Anka>
  <Gender>0</Gender>
  <BirthDate>2429015.693056</BirthDate>
  <Longitude>122.433333</Longitude>
  <Latitude>47.233333</Latitude>
  <TimeZone>8.000000</TimeZone>
  <DST>0.000000</DST>
  <City>Tacoma</City>
  <State>DE Delaware</State>
  <Country>USA</Country>
  <BDLoopUpMode>D</BDLoopUpMode>
  <RoddenRating>0</RoddenRating>
 </BirthInfo>
 <Events></Events>
 <DetailedNotes>Bowler. Concentration, did not pay attention to criticism, quiet. Looked old, the older man with glasses and a crewcut. LL 78. </DetailedNotes>
 <BirthdataPicklist></BirthdataPicklist>
 <AnimatedPicklist></AnimatedPicklist>
 <MuhurtaPicklist></MuhurtaPicklist>
 <FamilyInfo><GrandFather></GrandFather>
  <Father></Father>
  <Mother></Mother>
  <Caste></Caste>
  <Gotra></Gotra>
  <Address1></Address1>
  <Address2></Address2>
  <Address3></Address3>
  <Email></Email>
  <Phone></Phone>
  <Tags></Tags>
  <Unused1></Unused1>
  <Unused2></Unused2>
  <Unused3></Unused3>
 </FamilyInfo>
</BirthData>
